clockit/__init__.py
clockit/clockit.py
clockit_code-0.1.2.dist-info/METADATA
clockit_code-0.1.2.dist-info/WHEEL
clockit_code-0.1.2.dist-info/RECORD
