Metadata-Version: 2.4
Name: clockit-code
Version: 0.1.2
Summary: A super simple utility to time your python code.
Requires-Python: >=3.12
